lk_compat_helper/__init__.py
lk_compat_helper/commit_to_tag.py
linux_kernel_compat_helper-1.0.dist-info/LICENSE
linux_kernel_compat_helper-1.0.dist-info/METADATA
linux_kernel_compat_helper-1.0.dist-info/WHEEL
linux_kernel_compat_helper-1.0.dist-info/entry_points.txt
linux_kernel_compat_helper-1.0.dist-info/top_level.txt
linux_kernel_compat_helper-1.0.dist-info/RECORD
