Metadata-Version: 2.1
Name: linux-kernel-compat-helper
Version: 1.0
Summary: A helper to get exact versions based on commit changes to maintain compatibility across kernel versions.
Home-page: UNKNOWN
Author: Chaitanya Tata
Author-email: Chaitanya.tk17@gmail.com
License: GPL-2.0
Platform: UNKNOWN
License-File: LICENSE
Requires-Dist: PyGithub
Provides-Extra: dev
Requires-Dist: flake8 ; extra == 'dev'
Requires-Dist: coverage ; extra == 'dev'
Requires-Dist: mypy ; extra == 'dev'
Requires-Dist: black (>=20.8b0) ; extra == 'dev'
Requires-Dist: types-pyyaml ; extra == 'dev'
Requires-Dist: types-requests ; extra == 'dev'
Requires-Dist: types-jinja2 ; extra == 'dev'
Provides-Extra: docs
Requires-Dist: sphinx ; extra == 'docs'
Requires-Dist: sphinx-rtd-theme ; extra == 'docs'
